{
    "name": "root",
    "metadata": {
        "timer_format_version": "0.1.0",
        "start_time_seconds": "1676228064",
        "python_version": "3.9.13 (tags/v3.9.13:6de2ca5, May 17 2022, 16:36:42) [MSC v.1929 64 bit (AMD64)]",
        "command_line_arguments": "C:\\Unity Projects\\Minesweeper 1.0\\venv\\Scripts\\mlagents-learn --resume",
        "mlagents_version": "0.30.0",
        "mlagents_envs_version": "0.30.0",
        "communication_protocol_version": "1.5.0",
        "pytorch_version": "1.7.1+cu110",
        "numpy_version": "1.21.2",
        "end_time_seconds": "1676228075"
    },
    "total": 11.3728805,
    "count": 1,
    "self": 0.01009490000000035,
    "children": {
        "run_training.setup": {
            "total": 0.03711180000000014,
            "count": 1,
            "self": 0.03711180000000014
        },
        "TrainerController.start_learning": {
            "total": 11.3256738,
            "count": 1,
            "self": 0.00014080000000227244,
            "children": {
                "TrainerController._reset_env": {
                    "total": 10.7963919,
                    "count": 1,
                    "self": 10.7963919
                },
                "trainer_threads": {
                    "total": 6.99999999298484e-07,
                    "count": 1,
                    "self": 6.99999999298484e-07
                },
                "TrainerController._save_models": {
                    "total": 0.5291403999999993,
                    "count": 1,
                    "self": 0.0029921999999995563,
                    "children": {
                        "RLTrainer._checkpoint": {
                            "total": 0.5261481999999997,
                            "count": 1,
                            "self": 0.5261481999999997
                        }
                    }
                }
            }
        }
    }
}